django_ntfy/__init__.py
django_ntfy-0.1.1.dist-info/LICENSE
django_ntfy-0.1.1.dist-info/METADATA
django_ntfy-0.1.1.dist-info/WHEEL
django_ntfy-0.1.1.dist-info/RECORD
